aurora/__init__.py
aurora/types.py
aurora/base/__init__.py
aurora/base/app.py
aurora/base/base.py
aurora/base/input.py
aurora/base/render.py
aurora/demoapps/__init__.py
aurora/demoapps/helloworld/__init__.py
aurora/demoapps/helloworld/__main__.py
aurora/demoapps/imagedemo/__init__.py
aurora/demoapps/imagedemo/__main__.py
aurora/input/__init__.py
aurora/input/pygame/__init__.py
aurora/log/__init__.py
aurora/render/__init__.py
aurora/render/pygame/__init__.py
aurora/utils/__init__.py
aurora/utils/base.py
aurora/utils/color.py
aurora/utils/dict_base.py
aurora/utils/env.py
aurora/utils/font.py
aurora/utils/image.py
aurora_display_lib-1.0.0.dev20220104211509.dist-info/LICENSE
aurora_display_lib-1.0.0.dev20220104211509.dist-info/METADATA
aurora_display_lib-1.0.0.dev20220104211509.dist-info/WHEEL
aurora_display_lib-1.0.0.dev20220104211509.dist-info/top_level.txt
aurora_display_lib-1.0.0.dev20220104211509.dist-info/RECORD
