Metadata-Version: 2.1
Name: aurora-display-lib
Version: 1.0.0.dev20220104211509
Summary: Display library based on PIL/Pillow intended for Raspberry Pi applications running custom displays
Home-page: https://gitlab.com/aurora-display-lib
Author: Raphael "rGunti" Guntersweiler
Author-email: raphael+pip@gunti.cloud
License: MIT
Platform: UNKNOWN
Classifier: Development Status :: 4 - Beta
Classifier: Intended Audience :: Developers
Classifier: License :: OSI Approved :: MIT License
Classifier: Operating System :: OS Independent
Classifier: Programming Language :: Python
Classifier: Programming Language :: Python :: 3
Classifier: Programming Language :: Python :: 3 :: Only
Requires-Python: >=3.5
License-File: LICENSE
Requires-Dist: Pillow (>=8.4.0)
Requires-Dist: pygame (>=2.1.2)
Provides-Extra: deploy
Requires-Dist: bump2version ; extra == 'deploy'
Provides-Extra: test
Requires-Dist: testfixtures (>=1.2.0) ; extra == 'test'
Requires-Dist: pytest (>=3.4.0) ; extra == 'test'
